source_zoom/__init__.py
source_zoom/components.py
source_zoom/manifest.yaml
source_zoom/run.py
source_zoom/schemas/meeting_poll_results.json
source_zoom/schemas/meeting_polls.json
source_zoom/schemas/meeting_registrants.json
source_zoom/schemas/meeting_registration_questions.json
source_zoom/schemas/meetings.json
source_zoom/schemas/meetings_list_tmp.json
source_zoom/schemas/report_meeting_participants.json
source_zoom/schemas/report_meetings.json
source_zoom/schemas/report_webinar_participants.json
source_zoom/schemas/report_webinars.json
source_zoom/schemas/users.json
source_zoom/schemas/webinar_absentees.json
source_zoom/schemas/webinar_panelists.json
source_zoom/schemas/webinar_poll_results.json
source_zoom/schemas/webinar_polls.json
source_zoom/schemas/webinar_qna_results.json
source_zoom/schemas/webinar_registrants.json
source_zoom/schemas/webinar_registration_questions.json
source_zoom/schemas/webinar_tracking_sources.json
source_zoom/schemas/webinars.json
source_zoom/schemas/webinars_list_tmp.json
source_zoom/source.py
source_zoom/spec.yaml
airbyte_source_zoom-1.1.22.dist-info/METADATA
airbyte_source_zoom-1.1.22.dist-info/WHEEL
airbyte_source_zoom-1.1.22.dist-info/entry_points.txt
airbyte_source_zoom-1.1.22.dist-info/RECORD
